.gitignore
LICENSE
Makefile
README.md
pyproject.toml
setup.cfg
.github/pull_request_template.md
.github/ISSUE_TEMPLATE/bug_report.md
.github/ISSUE_TEMPLATE/feature_request.md
.github/workflows/cloudcoverage.yml
.github/workflows/coverage.yml
.github/workflows/publish_release.yml
.github/workflows/style.yml
cloudcoverage/action.yml
src/orquestra/integrations/braket/__init__.py
src/orquestra/integrations/braket/_utils.py
src/orquestra/integrations/braket/py.typed
src/orquestra/integrations/braket/runner.py
src/orquestra/integrations/braket/simulator.py
src/orquestra/integrations/braket/conversions/__init__.py
src/orquestra/integrations/braket/conversions/_circuit_conversions.py
src/orquestra_braket.egg-info/PKG-INFO
src/orquestra_braket.egg-info/SOURCES.txt
src/orquestra_braket.egg-info/dependency_links.txt
src/orquestra_braket.egg-info/not-zip-safe
src/orquestra_braket.egg-info/requires.txt
src/orquestra_braket.egg-info/top_level.txt
subtrees/z_quantum_actions/MANIFEST.in
subtrees/z_quantum_actions/Makefile
subtrees/z_quantum_actions/README.rst
subtrees/z_quantum_actions/pyproject.toml
subtrees/z_quantum_actions/pytest.ini
subtrees/z_quantum_actions/sample_setup.py
subtrees/z_quantum_actions/setup_extras.py
subtrees/z_quantum_actions/variables.mk
subtrees/z_quantum_actions/actions/coverage/action.yml
subtrees/z_quantum_actions/actions/publish-release/action.yml
subtrees/z_quantum_actions/actions/ssh_setup/action.yml
subtrees/z_quantum_actions/actions/style/action.yml
subtrees/z_quantum_actions/bin/get_next_version.py
subtrees/z_quantum_actions/tests/test_get_next_version.py
subtrees/z_quantum_actions/workflow-templates/coverage.yml
subtrees/z_quantum_actions/workflow-templates/publish-release.yml
subtrees/z_quantum_actions/workflow-templates/style.yml
tests/orquestra/braket/runner_test.py
tests/orquestra/braket/simulator_test.py